conjure/__init__.py
conjure/_version.py
conjure_client-0.2.0.dist-info/METADATA
conjure_client-0.2.0.dist-info/RECORD
conjure_client-0.2.0.dist-info/WHEEL
conjure_client-0.2.0.dist-info/top_level.txt
httpremoting/__init__.py
httpremoting/_version.py
