Metadata-Version: 2.1
Name: conjure-client
Version: 0.2.0
Summary: Conjure Python Library
Home-page: https://github.com/palantir/conjure-python-client
Author: Palantir Technologies, Inc.
Author-email: UNKNOWN
License: UNKNOWN
Platform: UNKNOWN
Requires-Dist: enum34
Requires-Dist: requests
Requires-Dist: typing
